desplice/__init__.py
desplice/main.py
desplice-0.0.2.dist-info/LICENSE
desplice-0.0.2.dist-info/METADATA
desplice-0.0.2.dist-info/WHEEL
desplice-0.0.2.dist-info/top_level.txt
desplice-0.0.2.dist-info/RECORD
