Metadata-Version: 2.1
Name: desplice
Version: 0.0.2
Summary: A Python library designed to process video files by removing duplicate frames
Home-page: https://github.com/manbehindthemadness/desplice
Author: Manbehindthemadness
Author-email: manbehindthemadness@gmail.com
Classifier: Programming Language :: Python :: 3
Classifier: License :: OSI Approved :: Apache Software License
Classifier: Operating System :: OS Independent
Requires-Python: >=3.10
License-File: LICENSE
Requires-Dist: opencv-python
Requires-Dist: Pillow
Requires-Dist: numpy
Requires-Dist: antidupe
